[
  {
    "ticker": "MU",
    "price": 451.64,
    "direction": "يقترب من خط مقاومة",
    "line_type": "مقاومة",
    "line_val": 482.52,
    "strength": "قوي",
    "cloud_color": "حمراء",
    "cloud_phase": "مستمرة",
    "volume_status": "ضعيف",
    "recommendation": "اتجاه محتمل مع الحذر",
    "targets": {
      "sl": 474.03,
      "tp1": 429.24,
      "tp2": 406.85,
      "tp3": 384.45
    },
    "last_date": "2026-04-21",
    "timeframe": "Daily (1D)",
    "summary": "يقترب من مقاومة قوية عند 482.52 في ظل استمرار السحابة الحمراء وحجم ضعيف، مما يشير لصعوبة الاختراق واحتمالية تراجع نحو 429.24"
  },
  {
    "ticker": "AVGO",
    "price": 401.33,
    "direction": "اخترق صعوداً خط مقاومة",
    "line_type": "مقاومة",
    "line_val": 353.56,
    "strength": "قوي",
    "cloud_color": "خضراء",
    "cloud_phase": "مستمرة",
    "volume_status": "ضعيف",
    "recommendation": "احتمال قوي لاستمرار الاتجاه",
    "targets": {
      "sl": 391.77,
      "tp1": 410.9,
      "tp2": 420.46,
      "tp3": 430.03
    },
    "last_date": "2026-04-21",
    "timeframe": "Daily (1D)",
    "summary": "اخترق بنجاح مقاومة قوية عند 353.56 مدعوماً بسحابة خضراء مستمرة رغم ضعف الحجم، مما يفتح المجال نحو 410.9 كهدف أول"
  },
  {
    "ticker": "AMD",
    "price": 282.54,
    "direction": "اخترق صعوداً خط مقاومة",
    "line_type": "مقاومة",
    "line_val": 271.27,
    "strength": "قوي",
    "cloud_color": "خضراء",
    "cloud_phase": "مستمرة",
    "volume_status": "ضعيف",
    "recommendation": "احتمال قوي لاستمرار الاتجاه",
    "targets": {
      "sl": 273.0,
      "tp1": 292.08,
      "tp2": 301.62,
      "tp3": 311.16
    },
    "last_date": "2026-04-21",
    "timeframe": "Daily (1D)",
    "summary": "حقق اختراقاً صعودياً لمقاومة قوية عند 271.27 بدعم من السحابة الخضراء المستمرة، مما يعزز التوقعات الإيجابية نحو 292.08"
  },
  {
    "ticker": "NVDA",
    "price": 199.54,
    "direction": "اخترق صعوداً خط مقاومة",
    "line_type": "مقاومة",
    "line_val": 197.11,
    "strength": "قوي",
    "cloud_color": "خضراء",
    "cloud_phase": "مستمرة",
    "volume_status": "ضعيف",
    "recommendation": "احتمال قوي لاستمرار الاتجاه",
    "targets": {
      "sl": 195.38,
      "tp1": 203.71,
      "tp2": 207.88,
      "tp3": 212.04
    },
    "last_date": "2026-04-21",
    "timeframe": "Daily (1D)",
    "summary": "نجح في اختراق مقاومة قوية عند 197.11 مدعوماً بسحابة خضراء مستمرة، مما يرجح استمرار الصعود نحو 203.71 كهدف مباشر"
  }
]