[
  {
    "ticker": "MU",
    "price": 511.18,
    "direction": "اخترق صعوداً خط مقاومة",
    "line_type": "مقاومة",
    "line_val": 485.99,
    "strength": "قوي",
    "cloud_color": "خضراء",
    "cloud_phase": "مستمرة",
    "volume_status": "ضعيف",
    "recommendation": "احتمال قوي لاستمرار الاتجاه",
    "targets": {
      "sl": 486.57,
      "tp1": 535.79,
      "tp2": 560.39,
      "tp3": 585.0
    },
    "last_date": "2026-04-30",
    "timeframe": "Daily (1D)",
    "summary": "اخترق السهم خط مقاومة قوي عند 485.99 ليصل إلى 511.18 مدعوماً بالسحابة الخضراء المستمرة، لكن الحجم الضعيف قد يحد من قوة الاندفاع صعوداً"
  },
  {
    "ticker": "AVGO",
    "price": 411.6,
    "direction": "اخترق صعوداً خط مقاومة",
    "line_type": "مقاومة",
    "line_val": 353.84,
    "strength": "قوي",
    "cloud_color": "خضراء",
    "cloud_phase": "مستمرة",
    "volume_status": "ضعيف",
    "recommendation": "احتمال قوي لاستمرار الاتجاه",
    "targets": {
      "sl": 400.82,
      "tp1": 422.38,
      "tp2": 433.16,
      "tp3": 443.94
    },
    "last_date": "2026-04-30",
    "timeframe": "Daily (1D)",
    "summary": "حقق السهم اختراقاً صعودياً مهماً لخط مقاومة قوي عند 353.84 ووصل إلى 411.6 مع دعم السحابة الخضراء، رغم أن ضعف الحجم يستدعي الحذر من تراجع محتمل"
  },
  {
    "ticker": "AMD",
    "price": 347.67,
    "direction": "اخترق صعوداً خط مقاومة",
    "line_type": "مقاومة",
    "line_val": 271.78,
    "strength": "قوي",
    "cloud_color": "خضراء",
    "cloud_phase": "مستمرة",
    "volume_status": "ضعيف",
    "recommendation": "احتمال قوي لاستمرار الاتجاه",
    "targets": {
      "sl": 333.9,
      "tp1": 361.45,
      "tp2": 375.22,
      "tp3": 389.0
    },
    "last_date": "2026-04-30",
    "timeframe": "Daily (1D)",
    "summary": "يواصل السهم ارتفاعه القوي بعد اختراق مقاومة هامة عند 271.78 ليصل إلى 347.67 مدعوماً بالسحابة الخضراء، لكن الحجم الضعيف قد يشير لتردد المشترين"
  },
  {
    "ticker": "NVDA",
    "price": 202.35,
    "direction": "اخترق صعوداً خط مقاومة",
    "line_type": "مقاومة",
    "line_val": 197.44,
    "strength": "قوي",
    "cloud_color": "خضراء",
    "cloud_phase": "مستمرة",
    "volume_status": "ضعيف",
    "recommendation": "احتمال قوي لاستمرار الاتجاه",
    "targets": {
      "sl": 196.43,
      "tp1": 208.26,
      "tp2": 214.18,
      "tp3": 220.1
    },
    "last_date": "2026-04-30",
    "timeframe": "Daily (1D)",
    "summary": "اخترق السهم بنجاح خط مقاومة قوي عند 197.44 ليصل إلى 202.35 وسط استمرار السحابة الخضراء الداعمة، لكن الحجم الضعيف يتطلب مراقبة لتأكيد الاتجاه"
  }
]